MANIFEST.in
README
RELEASE-VERSION
setup.py
version.py
nilsimsa/__init__.py
nilsimsa/test.py
nilsimsa.egg-info/PKG-INFO
nilsimsa.egg-info/SOURCES.txt
nilsimsa.egg-info/dependency_links.txt
nilsimsa.egg-info/entry_points.txt
nilsimsa.egg-info/not-zip-safe
nilsimsa.egg-info/top_level.txt
nilsimsa/test_data/1321151520-42e24b994d3e0497ead10ee2afd49e84.txt
nilsimsa/test_data/1328287020-f1473312784f0ac871f37ba2d3182af3.txt
nilsimsa/test_data/1331049600-d54345a2bf9f32a606c92f7c795624d3.txt
nilsimsa/test_data/1331187420-8e49a8b586e693d4814a4db7e0ceb6f5.txt
nilsimsa/test_data/1332493020-f96bf6e8312d58a10ad50df2f0069670.txt
nilsimsa/test_data/1332817740-5ea5517b01923a9bb49d351766431e3d.txt
nilsimsa/test_data/1337794475-880e87e7b8039fb1d3ba3bb5f8c119c0.txt
nilsimsa/test_data/1338103128-006193af403dcc90c962184df08960a3.txt
nilsimsa/test_data/1343165241-a7040e2d3228d46c595351b0b72e3e0e.txt
nilsimsa/test_data/1346026611-7274d49c61f17f29731565be72c554ed.txt
nilsimsa/test_data/1346445664-0808e0a8c8eed4d9d9fb316088782ca4.txt
nilsimsa/test_data/1347701841-29b665bda608d562d2c293f3fed5748a.txt
nilsimsa/test_data/1348854687-5babf7b3bb12f7dd0070c9c03c869401.txt
nilsimsa/test_data/1351184464-a56770fcfd732b6f266af4c8d70666ae.txt
nilsimsa/test_data/1352396387-81c1161097f9f00914e1b152ca4c0f46.txt
nilsimsa/test_data/1353015146-ff16590c8f8b3dd884ba50635aced6f5.txt
nilsimsa/test_data/1355115334-5d4f6caa5b4d857694caf39c83bb2233.txt
nilsimsa/test_data/1356111016-f1825429c7865e00626339d82c750619.txt
nilsimsa/test_data/1356289851-81efccbc5f0a5e0c69c79ebb88492126.txt
nilsimsa/test_data/1356495243-11b82d51aca4cdd805a5c30393cf6d2d.txt
nilsimsa/test_data/sid_table.p
nilsimsa/test_data/test_dict.p