Metadata-Version: 1.1
Name: nilsimsa
Version: 0.3.2
Summary: Locality-sensitive hashing
Home-page: https://github.com/diffeo/py-nilsimsa/
Author: nithintumma
Author-email: nithintumma gmail
License: X/MIT http://opensource.org/licenses/MIT
Keywords: python,nilsimsa,hash,locality-sensitive,duplicate detection
Platform: UNKNOWN
Classifier: Development Status :: 4 - Beta
Classifier: Intended Audience :: Developers
Classifier: Programming Language :: Python
Classifier: Topic :: Text Processing :: Indexing
Classifier: License :: OSI Approved :: MIT License
